rectab_io/__init__.py
rectab_io/analytics.py
rectab_io/auth.py
rectab_io/config.py
rectab_io/email_service.py
rectab_io-0.1.0.dist-info/METADATA
rectab_io-0.1.0.dist-info/WHEEL
rectab_io-0.1.0.dist-info/top_level.txt
rectab_io-0.1.0.dist-info/RECORD
